{
    "id": "scene8",
    "title": "贾母关切",
    "description": "宝玉和黛玉跟随丫鬟来到正厅，只见贾母早已坐在那里等候。贾母见二人进来，脸上立刻露出慈祥的笑容，招手让他们到身边坐下。'玉儿，你刚到贾府，还习惯吗？'贾母拉着黛玉的手关切地问道。黛玉忙起身回道：'多谢祖母关心，一切都好。'贾母又看向宝玉：'你这皮猴子，可不许欺负你林妹妹。'宝玉忙道：'祖母放心，我疼妹妹还来不及呢。'这时，王夫人和王熙凤也走了进来，正厅里顿时热闹起来。","choices": [
        {
            "text": "乖巧地坐在贾母身边",
            "luckChange": 6,
            "nextScene": "贾府的温暖"
        },
        {
            "text": "观察周围的环境和人物",
            "luckChange": 4,
            "nextScene": "贾府的规矩"
        }
    ]
}